agi_core/__init__.py
agi_core-2025.12.19.dist-info/METADATA
agi_core-2025.12.19.dist-info/WHEEL
agi_core-2025.12.19.dist-info/licenses/LICENSE
agi_core-2025.12.19.dist-info/RECORD
