Metadata-Version: 2.4
Name: agi-core
Version: 2025.12.19
Summary: AGI meta-package that installs agi-env, agi-node, and agi-cluster
Project-URL: Homepage, https://github.com/ThalesGroup/agilab
Project-URL: Issues, https://github.com/ThalesGroup/agilab/issues
Project-URL: Documentation, https://thalesgroup.github.io/agilab
Author-email: Jean-Pierre Morard <focus@thalesgroup.com>
License-File: LICENSE
Classifier: Development Status :: 3 - Alpha
Classifier: Intended Audience :: Developers
Classifier: Operating System :: MacOS
Classifier: Operating System :: Microsoft :: Windows
Classifier: Operating System :: POSIX :: Linux
Classifier: Programming Language :: Python :: 3
Classifier: Programming Language :: Python :: 3.11
Classifier: Programming Language :: Python :: 3.12
Classifier: Programming Language :: Python :: 3.13
Requires-Python: >=3.11
Requires-Dist: agi-cluster==2025.12.19
Requires-Dist: agi-env==2025.12.19
Requires-Dist: agi-node==2025.12.19
